cdk_hasan/__init__.py
cdk_hasan/py.typed
cdk_hasan/_jsii/__init__.py
cdk_hasan/_jsii/my-progen-project@0.0.0.jsii.tgz
cdk_hasan-0.0.0.dist-info/LICENSE
cdk_hasan-0.0.0.dist-info/METADATA
cdk_hasan-0.0.0.dist-info/WHEEL
cdk_hasan-0.0.0.dist-info/top_level.txt
cdk_hasan-0.0.0.dist-info/RECORD
